{
  "updated": "2026-07-11 22:12",
  "status": "ok",
  "nodes": {
    "Pi501": {
      "status": "ok",
      "cpu": {
        "total": 11.9,
        "user": 11.9,
        "system": 1.3,
        "idle": 86.3,
        "iowait": 0.3
      },
      "percpu": [
        7.6,
        12.9,
        11.4,
        15.9
      ],
      "ram": {
        "used_gb": 2.8,
        "total_gb": 7.87,
        "percent": 35.6,
        "available_gb": 5.07
      },
      "swap": {
        "used_mb": 1552.3,
        "total_mb": 2048.0,
        "percent": 75.8
      },
      "load": {
        "1min": 0.59,
        "5min": 1.05,
        "15min": 1.22,
        "cores": 4
      },
      "disks": [
        {
          "mount": "/",
          "device": "/dev/mmcblk0p2",
          "size_gb": 116.7,
          "used_gb": 47.5,
          "free_gb": 63.2,
          "percent": 40.7
        }
      ],
      "disk_io": {
        "read_mb": 0.2,
        "write_mb": 1969.6
      },
      "temperature_c": 58,
      "network": {
        "eth0": {
          "sent_mb": 0.0,
          "recv_mb": 0.0,
          "speed_kbps": 10240000.0
        }
      },
      "processes": {
        "total": 342,
        "running": 2,
        "sleeping": 247,
        "threads": 1198
      },
      "uptime": "10 days, 21:25:14",
      "containers": [
        {
          "name": "gallery backend",
          "status": "Up 5 days (healthy) gallery-downloader-backend"
        },
        {
          "name": "kavita",
          "status": "Up 6 days lscr.io/linuxserver/kavita:latest"
        },
        {
          "name": "subscription bot",
          "status": "Up 3 days (healthy) subscription-bot-subscription-bot"
        },
        {
          "name": "cadvisor",
          "status": "Up 7 days (healthy) gcr.io/cadvisor/cadvisor:latest"
        },
        {
          "name": "watchtower",
          "status": "Up 7 days (healthy) containrrr/watchtower"
        },
        {
          "name": "psclient",
          "status": "Up 7 days packetstream/psclient:latest"
        },
        {
          "name": "gallery frontend",
          "status": "Up 9 days gallery-downloader-frontend"
        },
        {
          "name": "gallery worker",
          "status": "Up 10 days gallery-downloader-worker"
        },
        {
          "name": "glances monitoring 1",
          "status": "Up 10 days nicolargo/glances:latest"
        },
        {
          "name": "uptime kuma",
          "status": "Up 21 hours (healthy) louislam/uptime-kuma:latest"
        },
        {
          "name": "wallos",
          "status": "Up 21 hours (healthy) bellamy/wallos:latest"
        },
        {
          "name": "ngninx app 1",
          "status": "Up 21 hours jc21/nginx-proxy-manager:latest"
        },
        {
          "name": "gallery jandapress",
          "status": "Up 10 days gallery-jandapress:local-arm64"
        },
        {
          "name": "Dashy",
          "status": "Up 10 days (healthy) lissy93/dashy:4.x"
        },
        {
          "name": "gallery redis",
          "status": "Up 10 days (healthy) redis:7-alpine"
        },
        {
          "name": "gallery postgres",
          "status": "Up 10 days (healthy) postgres:16-alpine"
        },
        {
          "name": "prowlarr",
          "status": "Up 10 days lscr.io/linuxserver/prowlarr:latest"
        },
        {
          "name": "portainer agent",
          "status": "Up 10 days portainer/agent:latest"
        }
      ],
      "container_count": 18,
      "services": "Gallery, Dashy, Hermes, NewsBot"
    },
    "Pi5": {
      "status": "ok",
      "cpu": {
        "total": 4.1,
        "user": 5.7,
        "system": 1.1,
        "idle": 92.8,
        "iowait": 0.4
      },
      "percpu": [
        6.8,
        5.4,
        2.4,
        3.0
      ],
      "ram": {
        "used_gb": 3.1,
        "total_gb": 7.87,
        "percent": 39.3,
        "available_gb": 4.78
      },
      "swap": {
        "used_mb": 164.2,
        "total_mb": 4096.0,
        "percent": 4.0
      },
      "load": {
        "1min": 0.24,
        "5min": 0.53,
        "15min": 0.59,
        "cores": 4
      },
      "disks": [
        {
          "mount": "/",
          "device": "/dev/mmcblk0p2",
          "size_gb": 116.7,
          "used_gb": 72.7,
          "free_gb": 38.1,
          "percent": 62.3
        },
        {
          "mount": "/",
          "device": "/dev/sda1",
          "size_gb": 915.8,
          "used_gb": 121.2,
          "free_gb": 748.0,
          "percent": 13.2
        }
      ],
      "disk_io": {
        "read_mb": 1002.4,
        "write_mb": 1547.8
      },
      "temperature_c": 55,
      "network": {
        "eth0": {
          "sent_mb": 0.0,
          "recv_mb": 0.0,
          "speed_kbps": 10240000.0
        }
      },
      "processes": {
        "total": 569,
        "running": 0,
        "sleeping": 477,
        "threads": 3321
      },
      "uptime": "10 days, 21:25:14",
      "containers": [
        {
          "name": "azuracast",
          "status": "Up 21 hours ghcr.io/azuracast/azuracast:stable"
        },
        {
          "name": "duckdns",
          "status": "Up 10 days lscr.io/linuxserver/duckdns:arm64v8-latest"
        },
        {
          "name": "uptime kuma",
          "status": "Up 10 days (healthy) louislam/uptime-kuma:2"
        },
        {
          "name": "duplicati 241",
          "status": "Up 10 days duplicati/duplicati"
        },
        {
          "name": "changedetection browser chrome 1",
          "status": "Up 10 days seleniarm/standalone-chromium:4.0.0-20211213"
        },
        {
          "name": "changedetection playwright chrome 1",
          "status": "Up 10 days browserless/chrome:latest"
        },
        {
          "name": "changedetection",
          "status": "Up 10 days ghcr.io/dgtlmoon/changedetection.io"
        },
        {
          "name": "glances monitoring 1",
          "status": "Up 10 days nicolargo/glances:latest"
        },
        {
          "name": "portainer agent",
          "status": "Up 10 days portainer/agent:latest"
        },
        {
          "name": "azuracast updater",
          "status": "Up 10 days ghcr.io/azuracast/updater:latest"
        }
      ],
      "container_count": 10,
      "services": "AzuraCast, DuckDNS, Media Server"
    },
    "Pi4": {
      "status": "ok",
      "cpu": {
        "total": 10.6,
        "user": 9.1,
        "system": 3.8,
        "idle": 86.9,
        "iowait": 0.1
      },
      "percpu": [
        9.9,
        9.4,
        11.9,
        11.2
      ],
      "ram": {
        "used_gb": 1.83,
        "total_gb": 7.64,
        "percent": 24.0,
        "available_gb": 5.81
      },
      "swap": {
        "used_mb": 3.2,
        "total_mb": 512.0,
        "percent": 0.6
      },
      "load": {
        "1min": 0.31,
        "5min": 0.49,
        "15min": 0.6,
        "cores": 4
      },
      "disks": [
        {
          "mount": "/",
          "device": "/dev/mmcblk0p2",
          "size_gb": 115.3,
          "used_gb": 31.6,
          "free_gb": 77.9,
          "percent": 27.4
        }
      ],
      "disk_io": {
        "read_mb": 1.2,
        "write_mb": 478.8
      },
      "temperature_c": 38,
      "network": {
        "eth0": {
          "sent_mb": 0.0,
          "recv_mb": 0.0,
          "speed_kbps": 10240000.0
        }
      },
      "processes": {
        "total": 267,
        "running": 0,
        "sleeping": 169,
        "threads": 940
      },
      "uptime": "10 days, 21:25:18",
      "containers": [
        {
          "name": "cadvisor",
          "status": "Up 7 days (healthy) gcr.io/cadvisor/cadvisor:latest"
        },
        {
          "name": "cve grafana",
          "status": "Up 21 hours grafana/grafana:latest"
        },
        {
          "name": "cve prometheus",
          "status": "Up 21 hours prom/prometheus:latest"
        },
        {
          "name": "changedetection",
          "status": "Up 10 days ghcr.io/dgtlmoon/changedetection.io"
        },
        {
          "name": "changedetection browser chrome 1",
          "status": "Up 10 days seleniarm/standalone-chromium:latest"
        },
        {
          "name": "changedetection playwright chrome 1",
          "status": "Up 10 days browserless/chrome:latest"
        },
        {
          "name": "Dashy",
          "status": "Up 10 days (healthy) lissy93/dashy:4.x"
        },
        {
          "name": "glances monitoring 1",
          "status": "Up 10 days nicolargo/glances:latest"
        },
        {
          "name": "cve report",
          "status": "Up 10 days nginx:alpine"
        },
        {
          "name": "cve alertmanager",
          "status": "Up 10 days prom/alertmanager:latest"
        },
        {
          "name": "cve pushgateway",
          "status": "Up 10 days prom/pushgateway:latest"
        },
        {
          "name": "portainer",
          "status": "Up 10 days portainer/portainer-ce:lts"
        },
        {
          "name": "duplicati 241",
          "status": "Up 10 days duplicati/duplicati"
        }
      ],
      "container_count": 13,
      "services": "Pi-hole, NPM, Wallos, Pi.Alert"
    }
  },
  "radio": {
    "station": "dublincalling",
    "is_online": true,
    "is_live": false,
    "now_playing": {
      "title": "Chasing A Girl (Inside A Car) (Peel Session)",
      "artist": "Mercury Rev",
      "album": "Lego My Ego",
      "genre": "Rock",
      "art": "https://dublincalling.duckdns.org/api/station/dublincalling/art/32f387d98d94432700b51d59-1782770890.jpg",
      "duration": 609,
      "elapsed": 338
    },
    "playing_next": {
      "title": "Mighty Diamonds - Reggaeman",
      "artist": "Mighty Diamonds"
    },
    "listeners": 0,
    "listen_url": "https://dublincalling.duckdns.org/listen/dublincalling/radio.mp3",
    "history": [
      {
        "title": "Wait And See",
        "artist": "Stiff Little Fingers",
        "played_at": 1783803729
      },
      {
        "title": "Back In Denim",
        "artist": "Turbonegro",
        "played_at": 1783803482
      },
      {
        "title": "Howza Bouta Kiss Babe??!",
        "artist": "The Toy Dolls",
        "played_at": 1783803311
      },
      {
        "title": "Teenage Lobotomy",
        "artist": "Ramones",
        "played_at": 1783803190
      },
      {
        "title": "Garden Song",
        "artist": "Herman Dune",
        "played_at": 1783802944
      }
    ]
  }
}