{
  "updated": "2026-07-11 05:12",
  "status": "ok",
  "nodes": {
    "Pi501": {
      "status": "ok",
      "cpu": {
        "total": 13.3,
        "user": 11.8,
        "system": 2.1,
        "idle": 85.2,
        "iowait": 0.6
      },
      "percpu": [
        10.3,
        22.1,
        8.5,
        12.7
      ],
      "ram": {
        "used_gb": 2.72,
        "total_gb": 7.87,
        "percent": 34.5,
        "available_gb": 5.15
      },
      "swap": {
        "used_mb": 1565.3,
        "total_mb": 2048.0,
        "percent": 76.4
      },
      "load": {
        "1min": 1.39,
        "5min": 1.45,
        "15min": 1.36,
        "cores": 4
      },
      "disks": [
        {
          "mount": "/",
          "device": "/dev/mmcblk0p2",
          "size_gb": 116.7,
          "used_gb": 47.5,
          "free_gb": 63.2,
          "percent": 40.7
        }
      ],
      "disk_io": {
        "read_mb": 2.2,
        "write_mb": 1977.6
      },
      "temperature_c": 57,
      "network": {
        "eth0": {
          "sent_mb": 0.0,
          "recv_mb": 0.0,
          "speed_kbps": 10240000.0
        }
      },
      "processes": {
        "total": 342,
        "running": 2,
        "sleeping": 248,
        "threads": 1194
      },
      "uptime": "10 days, 4:25:28",
      "containers": [
        {
          "name": "gallery backend",
          "status": "Up 4 days (healthy) gallery-downloader-backend"
        },
        {
          "name": "kavita",
          "status": "Up 5 days lscr.io/linuxserver/kavita:latest"
        },
        {
          "name": "subscription bot",
          "status": "Up 2 days (healthy) subscription-bot-subscription-bot"
        },
        {
          "name": "cadvisor",
          "status": "Up 7 days (healthy) gcr.io/cadvisor/cadvisor:latest"
        },
        {
          "name": "watchtower",
          "status": "Up 7 days (healthy) containrrr/watchtower"
        },
        {
          "name": "psclient",
          "status": "Up 7 days packetstream/psclient:latest"
        },
        {
          "name": "gallery frontend",
          "status": "Up 8 days gallery-downloader-frontend"
        },
        {
          "name": "gallery worker",
          "status": "Up 9 days gallery-downloader-worker"
        },
        {
          "name": "glances monitoring 1",
          "status": "Up 10 days nicolargo/glances:latest"
        },
        {
          "name": "uptime kuma",
          "status": "Up 4 hours (healthy) louislam/uptime-kuma:latest"
        },
        {
          "name": "wallos",
          "status": "Up 4 hours (healthy) bellamy/wallos:latest"
        },
        {
          "name": "ngninx app 1",
          "status": "Up 4 hours jc21/nginx-proxy-manager:latest"
        },
        {
          "name": "gallery jandapress",
          "status": "Up 9 days gallery-jandapress:local-arm64"
        },
        {
          "name": "Dashy",
          "status": "Up 10 days (healthy) lissy93/dashy:4.x"
        },
        {
          "name": "gallery redis",
          "status": "Up 9 days (healthy) redis:7-alpine"
        },
        {
          "name": "gallery postgres",
          "status": "Up 9 days (healthy) postgres:16-alpine"
        },
        {
          "name": "prowlarr",
          "status": "Up 10 days lscr.io/linuxserver/prowlarr:latest"
        },
        {
          "name": "portainer agent",
          "status": "Up 10 days portainer/agent:latest"
        }
      ],
      "container_count": 18,
      "services": "Gallery, Dashy, Hermes, NewsBot"
    },
    "Pi5": {
      "status": "ok",
      "cpu": {
        "total": 3.2,
        "user": 5.5,
        "system": 1.0,
        "idle": 92.9,
        "iowait": 0.5
      },
      "percpu": [
        2.0,
        3.8,
        6.3,
        1.4
      ],
      "ram": {
        "used_gb": 3.03,
        "total_gb": 7.87,
        "percent": 38.5,
        "available_gb": 4.84
      },
      "swap": {
        "used_mb": 164.2,
        "total_mb": 4096.0,
        "percent": 4.0
      },
      "load": {
        "1min": 0.25,
        "5min": 0.38,
        "15min": 0.44,
        "cores": 4
      },
      "disks": [
        {
          "mount": "/",
          "device": "/dev/mmcblk0p2",
          "size_gb": 116.7,
          "used_gb": 72.7,
          "free_gb": 38.1,
          "percent": 62.3
        },
        {
          "mount": "/",
          "device": "/dev/sda1",
          "size_gb": 915.8,
          "used_gb": 121.4,
          "free_gb": 747.9,
          "percent": 13.3
        }
      ],
      "disk_io": {
        "read_mb": 949.5,
        "write_mb": 1587.2
      },
      "temperature_c": 54,
      "network": {
        "eth0": {
          "sent_mb": 0.0,
          "recv_mb": 0.0,
          "speed_kbps": 10240000.0
        }
      },
      "processes": {
        "total": 571,
        "running": 0,
        "sleeping": 477,
        "threads": 3320
      },
      "uptime": "10 days, 4:25:28",
      "containers": [
        {
          "name": "azuracast",
          "status": "Up 4 hours ghcr.io/azuracast/azuracast:stable"
        },
        {
          "name": "duckdns",
          "status": "Up 10 days lscr.io/linuxserver/duckdns:arm64v8-latest"
        },
        {
          "name": "uptime kuma",
          "status": "Up 10 days (healthy) louislam/uptime-kuma:2"
        },
        {
          "name": "duplicati 241",
          "status": "Up 10 days duplicati/duplicati"
        },
        {
          "name": "changedetection browser chrome 1",
          "status": "Up 10 days seleniarm/standalone-chromium:4.0.0-20211213"
        },
        {
          "name": "changedetection playwright chrome 1",
          "status": "Up 10 days browserless/chrome:latest"
        },
        {
          "name": "changedetection",
          "status": "Up 10 days ghcr.io/dgtlmoon/changedetection.io"
        },
        {
          "name": "glances monitoring 1",
          "status": "Up 10 days nicolargo/glances:latest"
        },
        {
          "name": "portainer agent",
          "status": "Up 10 days portainer/agent:latest"
        },
        {
          "name": "azuracast updater",
          "status": "Up 10 days ghcr.io/azuracast/updater:latest"
        }
      ],
      "container_count": 10,
      "services": "AzuraCast, DuckDNS, Media Server"
    },
    "Pi4": {
      "status": "ok",
      "cpu": {
        "total": 11.1,
        "user": 8.8,
        "system": 3.6,
        "idle": 87.5,
        "iowait": 0.1
      },
      "percpu": [
        11.1,
        11.6,
        11.4,
        10.5
      ],
      "ram": {
        "used_gb": 1.77,
        "total_gb": 7.64,
        "percent": 23.2,
        "available_gb": 5.87
      },
      "swap": {
        "used_mb": 3.2,
        "total_mb": 512.0,
        "percent": 0.6
      },
      "load": {
        "1min": 0.19,
        "5min": 0.49,
        "15min": 0.59,
        "cores": 4
      },
      "disks": [
        {
          "mount": "/",
          "device": "/dev/mmcblk0p2",
          "size_gb": 115.3,
          "used_gb": 31.4,
          "free_gb": 78.1,
          "percent": 27.2
        }
      ],
      "disk_io": {
        "read_mb": 3.8,
        "write_mb": 481.9
      },
      "temperature_c": 36,
      "network": {
        "eth0": {
          "sent_mb": 0.0,
          "recv_mb": 0.0,
          "speed_kbps": 10240000.0
        }
      },
      "processes": {
        "total": 266,
        "running": 0,
        "sleeping": 169,
        "threads": 933
      },
      "uptime": "10 days, 4:25:32",
      "containers": [
        {
          "name": "cadvisor",
          "status": "Up 7 days (healthy) gcr.io/cadvisor/cadvisor:latest"
        },
        {
          "name": "cve grafana",
          "status": "Up 4 hours grafana/grafana:latest"
        },
        {
          "name": "cve prometheus",
          "status": "Up 4 hours prom/prometheus:latest"
        },
        {
          "name": "changedetection",
          "status": "Up 10 days ghcr.io/dgtlmoon/changedetection.io"
        },
        {
          "name": "changedetection browser chrome 1",
          "status": "Up 10 days seleniarm/standalone-chromium:latest"
        },
        {
          "name": "changedetection playwright chrome 1",
          "status": "Up 10 days browserless/chrome:latest"
        },
        {
          "name": "Dashy",
          "status": "Up 10 days (healthy) lissy93/dashy:4.x"
        },
        {
          "name": "glances monitoring 1",
          "status": "Up 10 days nicolargo/glances:latest"
        },
        {
          "name": "cve report",
          "status": "Up 10 days nginx:alpine"
        },
        {
          "name": "cve alertmanager",
          "status": "Up 10 days prom/alertmanager:latest"
        },
        {
          "name": "cve pushgateway",
          "status": "Up 10 days prom/pushgateway:latest"
        },
        {
          "name": "portainer",
          "status": "Up 10 days portainer/portainer-ce:lts"
        },
        {
          "name": "duplicati 241",
          "status": "Up 10 days duplicati/duplicati"
        }
      ],
      "container_count": 13,
      "services": "Pi-hole, NPM, Wallos, Pi.Alert"
    }
  },
  "radio": {
    "station": "dublincalling",
    "is_online": true,
    "is_live": false,
    "now_playing": {
      "title": "John Peel 2003-10-02",
      "artist": "John Peel (R1)",
      "album": "from RA",
      "genre": "",
      "art": "https://dublincalling.duckdns.org/api/station/dublincalling/art/a3c3d8806eb7a1a1efa94bd7",
      "duration": 7082,
      "elapsed": 1677
    },
    "playing_next": {
      "title": "Misty Morning, Albert Bridge",
      "artist": "The Pogues"
    },
    "listeners": 0,
    "listen_url": "https://dublincalling.duckdns.org/listen/dublincalling/radio.mp3",
    "history": [
      {
        "title": "She's My Scorcher",
        "artist": "toots and the maytals",
        "played_at": 1783741315
      },
      {
        "title": "Cold I up",
        "artist": "Johnny Clarke",
        "played_at": 1783741135
      },
      {
        "title": "I Wanna Get in Your Pants",
        "artist": "The Cramps",
        "played_at": 1783740879
      },
      {
        "title": "a design for life",
        "artist": "John Peel Festive Fifty 1996",
        "played_at": 1783740614
      },
      {
        "title": "Rendevouz With Anus",
        "artist": "Turbonegro",
        "played_at": 1783740495
      }
    ]
  }
}