{
  "updated": "2026-07-23 13:12",
  "status": "ok",
  "nodes": {
    "Pi501": {
      "status": "ok",
      "cpu": {
        "total": 6.3,
        "user": 4.0,
        "system": 2.3,
        "idle": 93.2,
        "iowait": 0.2
      },
      "percpu": [
        7.8,
        6.2,
        5.7,
        7.1
      ],
      "ram": {
        "used_gb": 1.84,
        "total_gb": 7.87,
        "percent": 23.4,
        "available_gb": 6.03
      },
      "swap": {
        "used_mb": 0.0,
        "total_mb": 2048.0,
        "percent": 0.0
      },
      "load": {
        "1min": 0.71,
        "5min": 0.83,
        "15min": 0.76,
        "cores": 4
      },
      "disks": [
        {
          "mount": "/",
          "device": "/dev/mmcblk0p2",
          "size_gb": 116.7,
          "used_gb": 48.9,
          "free_gb": 61.8,
          "percent": 42.0
        }
      ],
      "disk_io": {
        "read_mb": 60.0,
        "write_mb": 1937.9
      },
      "temperature_c": 51,
      "network": {
        "eth0": {
          "sent_mb": 0.0,
          "recv_mb": 0.0,
          "speed_kbps": 10240000.0
        }
      },
      "processes": {
        "total": 333,
        "running": 0,
        "sleeping": 237,
        "threads": 1072
      },
      "uptime": "5:37:26",
      "containers": [
        {
          "name": "gallery worker",
          "status": "Up 4 hours gallery-downloader-worker"
        },
        {
          "name": "gallery backend",
          "status": "Up 4 hours (healthy) gallery-downloader-backend"
        },
        {
          "name": "kavita",
          "status": "Up 4 hours lscr.io/linuxserver/kavita:latest"
        },
        {
          "name": "subscription bot",
          "status": "Up 4 hours (healthy) subscription-bot-subscription-bot"
        },
        {
          "name": "cadvisor",
          "status": "Up 4 hours (healthy) gcr.io/cadvisor/cadvisor:latest"
        },
        {
          "name": "watchtower",
          "status": "Up 4 hours (healthy) containrrr/watchtower"
        },
        {
          "name": "psclient",
          "status": "Up 4 hours packetstream/psclient:latest"
        },
        {
          "name": "gallery frontend",
          "status": "Up 4 hours gallery-downloader-frontend"
        },
        {
          "name": "glances monitoring 1",
          "status": "Up 4 hours nicolargo/glances:latest"
        },
        {
          "name": "uptime kuma",
          "status": "Up 4 hours (healthy) louislam/uptime-kuma:latest"
        },
        {
          "name": "wallos",
          "status": "Up 4 hours (healthy) bellamy/wallos:latest"
        },
        {
          "name": "ngninx app 1",
          "status": "Up 4 hours jc21/nginx-proxy-manager:latest"
        },
        {
          "name": "gallery jandapress",
          "status": "Up 4 hours gallery-jandapress:local-arm64"
        },
        {
          "name": "Dashy",
          "status": "Up 4 hours (healthy) lissy93/dashy:4.x"
        },
        {
          "name": "gallery redis",
          "status": "Up 4 hours (healthy) redis:7-alpine"
        },
        {
          "name": "gallery postgres",
          "status": "Up 4 hours (healthy) postgres:16-alpine"
        },
        {
          "name": "prowlarr",
          "status": "Up 4 hours lscr.io/linuxserver/prowlarr:latest"
        },
        {
          "name": "portainer agent",
          "status": "Up 4 hours portainer/agent:latest"
        }
      ],
      "container_count": 18,
      "services": "Gallery, Dashy, Hermes, NewsBot"
    },
    "Pi5": {
      "status": "ok",
      "cpu": {
        "total": 6.2,
        "user": 5.1,
        "system": 0.9,
        "idle": 93.4,
        "iowait": 0.6
      },
      "percpu": [
        5.5,
        6.8,
        5.6,
        8.1
      ],
      "ram": {
        "used_gb": 2.53,
        "total_gb": 7.87,
        "percent": 32.1,
        "available_gb": 5.34
      },
      "swap": {
        "used_mb": 0.0,
        "total_mb": 4096.0,
        "percent": 0.0
      },
      "load": {
        "1min": 0.97,
        "5min": 0.72,
        "15min": 0.57,
        "cores": 4
      },
      "disks": [
        {
          "mount": "/",
          "device": "/dev/mmcblk0p2",
          "size_gb": 116.7,
          "used_gb": 72.7,
          "free_gb": 38.0,
          "percent": 62.3
        },
        {
          "mount": "/",
          "device": "/dev/sda1",
          "size_gb": 915.8,
          "used_gb": 120.6,
          "free_gb": 748.6,
          "percent": 13.2
        }
      ],
      "disk_io": {
        "read_mb": 661.1,
        "write_mb": 1205.8
      },
      "temperature_c": 50,
      "network": {
        "eth0": {
          "sent_mb": 0.0,
          "recv_mb": 0.0,
          "speed_kbps": 10240000.0
        }
      },
      "processes": {
        "total": 569,
        "running": 0,
        "sleeping": 472,
        "threads": 3239
      },
      "uptime": "5:37:27",
      "containers": [
        {
          "name": "azuracast",
          "status": "Up 6 hours ghcr.io/azuracast/azuracast:stable"
        },
        {
          "name": "duckdns",
          "status": "Up 6 hours lscr.io/linuxserver/duckdns:arm64v8-latest"
        },
        {
          "name": "uptime kuma",
          "status": "Up 6 hours (healthy) louislam/uptime-kuma:2"
        },
        {
          "name": "changedetection browser chrome 1",
          "status": "Up 6 hours seleniarm/standalone-chromium:4.0.0-20211213"
        },
        {
          "name": "changedetection playwright chrome 1",
          "status": "Up 6 hours browserless/chrome:latest"
        },
        {
          "name": "changedetection",
          "status": "Up 6 hours ghcr.io/dgtlmoon/changedetection.io"
        },
        {
          "name": "glances monitoring 1",
          "status": "Up 6 hours nicolargo/glances:latest"
        },
        {
          "name": "portainer agent",
          "status": "Up 6 hours portainer/agent:latest"
        },
        {
          "name": "azuracast updater",
          "status": "Up 6 hours ghcr.io/azuracast/updater:latest"
        }
      ],
      "container_count": 9,
      "services": "AzuraCast, DuckDNS, Media Server"
    },
    "Pi4": {
      "status": "ok",
      "cpu": {
        "total": 17.3,
        "user": 12.2,
        "system": 5.7,
        "idle": 81.8,
        "iowait": 0.2
      },
      "percpu": [
        16.8,
        17.9,
        17.3,
        17.7
      ],
      "ram": {
        "used_gb": 1.83,
        "total_gb": 7.64,
        "percent": 24.0,
        "available_gb": 5.8
      },
      "swap": {
        "used_mb": 0.0,
        "total_mb": 512.0,
        "percent": 0.0
      },
      "load": {
        "1min": 0.7,
        "5min": 0.96,
        "15min": 0.98,
        "cores": 4
      },
      "disks": [
        {
          "mount": "/",
          "device": "/dev/mmcblk0p2",
          "size_gb": 115.3,
          "used_gb": 33.5,
          "free_gb": 76.0,
          "percent": 29.0
        }
      ],
      "disk_io": {
        "read_mb": 5.5,
        "write_mb": 735.7
      },
      "temperature_c": 37,
      "network": {
        "eth0": {
          "sent_mb": 0.0,
          "recv_mb": 0.0,
          "speed_kbps": 10240000.0
        }
      },
      "processes": {
        "total": 290,
        "running": 0,
        "sleeping": 194,
        "threads": 1012
      },
      "uptime": "5:37:30",
      "containers": [
        {
          "name": "politicosaas app 1",
          "status": "Up 6 hours politicosaas-app"
        },
        {
          "name": "politicosaas postgres 1",
          "status": "Up 6 hours (healthy) postgres:15-alpine"
        },
        {
          "name": "politicosaas meilisearch 1",
          "status": "Up 6 hours getmeili/meilisearch:v1.12"
        },
        {
          "name": "cadvisor",
          "status": "Up 6 hours (healthy) gcr.io/cadvisor/cadvisor:latest"
        },
        {
          "name": "cve grafana",
          "status": "Up 6 hours grafana/grafana:latest"
        },
        {
          "name": "cve prometheus",
          "status": "Up 6 hours prom/prometheus:latest"
        },
        {
          "name": "changedetection",
          "status": "Up 6 hours ghcr.io/dgtlmoon/changedetection.io"
        },
        {
          "name": "changedetection browser chrome 1",
          "status": "Up 6 hours seleniarm/standalone-chromium:latest"
        },
        {
          "name": "changedetection playwright chrome 1",
          "status": "Up 6 hours browserless/chrome:latest"
        },
        {
          "name": "Dashy",
          "status": "Up 6 hours (healthy) lissy93/dashy:4.x"
        },
        {
          "name": "glances monitoring 1",
          "status": "Up 6 hours nicolargo/glances:latest"
        },
        {
          "name": "cve report",
          "status": "Up 6 hours nginx:alpine"
        },
        {
          "name": "cve alertmanager",
          "status": "Up 6 hours prom/alertmanager:latest"
        },
        {
          "name": "cve pushgateway",
          "status": "Up 6 hours prom/pushgateway:latest"
        },
        {
          "name": "portainer",
          "status": "Up 6 hours portainer/portainer-ce:lts"
        },
        {
          "name": "duplicati 241",
          "status": "Up 6 hours duplicati/duplicati"
        }
      ],
      "container_count": 16,
      "services": "Pi-hole, NPM, Wallos, Pi.Alert"
    }
  },
  "radio": {
    "station": "dublincalling",
    "is_online": true,
    "is_live": false,
    "now_playing": {
      "title": "underdog session 2024-05-24",
      "artist": "",
      "album": "",
      "genre": "",
      "art": "https://dublincalling.duckdns.org/api/station/dublincalling/art/9a930147a6d15dcc4681e37e",
      "duration": 5267,
      "elapsed": 4457
    },
    "playing_next": {
      "title": "John Peel 2003-05-08",
      "artist": "John Peel (R1)"
    },
    "listeners": 0,
    "listen_url": "https://dublincalling.duckdns.org/listen/dublincalling/radio.mp3",
    "history": [
      {
        "title": "Lets Jump",
        "artist": "Toots and The Maytals",
        "played_at": 1784804152
      },
      {
        "title": "Neon Lights Flashing",
        "artist": "Gregory Isaacs & Dennis Brown",
        "played_at": 1784803747
      },
      {
        "title": "Experiment Conclusion",
        "artist": "Dr. & the Crippens",
        "played_at": 1784803742
      },
      {
        "title": "Cramp Stomp",
        "artist": "The Cramps",
        "played_at": 1784803540
      },
      {
        "title": "/ Shut Down",
        "artist": "The Undertones",
        "played_at": 1784803335
      }
    ]
  }
}