{
  "updated": "2026-07-23T00:20:48.152031+01:00",
  "items": [
    {
      "title": "Conan O’Brien Explains His Horrifying New Hairdo",
      "source": "Consequence of Sound (US)",
      "link": "https://consequence.net/2026/07/conan-obrien-hairdo-explained-sunburn/",
      "summary": "Did Larry King dye his hair red? Conan O&#8217;Brien Explains His Horrifying New Hairdo Liz Shannon Miller",
      "date": "2026-07-22T19:46:57",
      "image": ""
    },
    {
      "title": "Marian Keyes' Dublin-based drama set to return after leaving viewers 'hooked'",
      "source": "Dublin Live News",
      "link": "https://www.dublinlive.ie/news/celebs/marian-keyes-dublin-based-drama-34336507",
      "summary": "The show, based on Marian Keyes' bestselling books, was a hit when it aired last year and RTÉ has now confirmed a new series.",
      "date": "2026-07-22T21:33:25",
      "image": ""
    },
    {
      "title": "Man, 30s, dies in Irish road collision involving van as Gardai issue appeal",
      "source": "Dublin Live News",
      "link": "https://www.dublinlive.ie/news/man-30s-dies-irish-road-34336450",
      "summary": "The man was pronounced dead at the scene of the fatal collision on the R693 near Freshford, Co Kilkenny",
      "date": "2026-07-22T20:40:39",
      "image": ""
    },
    {
      "title": "Olivia Dean & Lola Young Boost British Recorded Exports to New Record High",
      "source": "Billboard (US)",
      "link": "https://www.billboard.com/pro/olivia-dean-lola-young-british-recorded-exports-new-record/",
      "summary": "The latest figure is up 50% compared to data recorded by the BPI five years ago.",
      "date": "2026-07-22T23:00:00",
      "image": ""
    },
    {
      "title": "Tony Thorpe, Guitarist & Songwriter for Glam Rockers The Rubettes, Dies at 80",
      "source": "Billboard (US)",
      "link": "https://www.billboard.com/music/rock/tony-thorpe-death-rubettes-guitarist-songwriter-1236301131/",
      "summary": "The musician is remembered by family &#38; former bandmate Alan Williams in a heartfelt tribute.",
      "date": "2026-07-22T22:53:21",
      "image": ""
    },
    {
      "title": "Belmont University to House Johnny Cash’s Personal Archives",
      "source": "Billboard (US)",
      "link": "https://www.billboard.com/music/country/johnny-cash-personal-archives-belmont-university-1236300861/",
      "summary": "The archives will be part of the new Johnny Cash Learning Center at Belmont University's Mike Curb College of Entertainment &#38; Music Business.",
      "date": "2026-07-22T22:36:37",
      "image": ""
    },
    {
      "title": "Charli XCX – “If You Take Away The Music, Then What Has She Got?”",
      "source": "Stereogum (US)",
      "link": "https://stereogum.com/2506037/charli-xcx-if-you-take-away-the-music-then-what-has-she-got/music/",
      "summary": "Only two days until Music, Fashion, Film, but Charli XCX isn't done with the rollout. We got the latest single \"Camera\" on Tuesday (July 21), but she still has B-sides in store. Previous B-sides are \"I Keep Thinking About You Every Single Day And Night\" and \"Playboy Bunny,\" and today she's sharing the final B-side, \"If You Take Away The Music, Then What Has She Got?,\" which she debuted in Brooklyn the other weekend.",
      "date": "2026-07-22T20:06:38",
      "image": ""
    },
    {
      "title": "Trusselina – “Gastro” & “Trusselina Archimboldi”",
      "source": "Stereogum (US)",
      "link": "https://stereogum.com/2506032/trusselina-gastro-trusselina-archimboldi/music/",
      "summary": "Mikaela Oppenheimer used to be in the Brooklyn emo band Hello Mary, while Hayden McGarvey is a former member of the Philadelphia shoegaze crew Bleary Eyed. The two of them got to know each other when their bands toured together in 2024, and now they've joined forces to form Trusselina, a new duo whose music doesn't sound anything like their previous two bands.",
      "date": "2026-07-22T19:27:30",
      "image": ""
    },
    {
      "title": "Wild Pink – “500 Is The New 250”",
      "source": "Stereogum (US)",
      "link": "https://stereogum.com/2506024/wild-pink-250-is-the-new-500/music/",
      "summary": "Wild Pink's upcoming album Still Coming Down feels a lot like MJ Lenderman cosplay, but can we even be mad about it? It sounds good, and Lenderman himself works on the record, so he must not mind. \"500 Is The New 250\" — which follows \"Round Of Applause At The End Of The World\" and \"Box Store\" — has a man taking a Cybertruck to his favorite bar (poetically called Hard Luck) to bet on his phone and drink alone.",
      "date": "2026-07-22T19:10:35",
      "image": ""
    },
    {
      "title": "29 New Songs Out Today",
      "source": "BrooklynVegan (US)",
      "link": "https://www.brooklynvegan.com/29-new-songs-out-today-40/",
      "summary": "Hear new songs by Krill, Afghan Whigs, Goldie, Amon Amarth, Noname, Origami Angel, Wild Pink, The Tubs, Russian Circles, Nigel Godrich &#038; Dhani Harrison, more",
      "date": "2026-07-22T22:55:24",
      "image": ""
    },
    {
      "title": "Union Pool fell for Greg Freeman… and vice versa! (pics, video)",
      "source": "BrooklynVegan (US)",
      "link": "https://www.brooklynvegan.com/union-pool-fell-for-greg-freeman-and-vice-versa-pics-video/",
      "summary": "Hours after announcing his new album, he played the whole thing at an intimate Brooklyn show with Wendy Eisenberg.",
      "date": "2026-07-22T22:18:13",
      "image": ""
    },
    {
      "title": "Tour news: Dom Dolla / Peggy Gou / Basement Jaxx, Don Was, Ian Sweet, Thor & Friends, more",
      "source": "BrooklynVegan (US)",
      "link": "https://www.brooklynvegan.com/tour-news-dom-dolla-peggy-gou-basement-jaxx-don-was-ian-sweet-thor-friends-more/",
      "summary": "Plus: Bounding Souls, Face to Face, Protomartyr and more tour, festival and show news.",
      "date": "2026-07-22T22:14:11",
      "image": ""
    },
    {
      "title": "What Musicians Said About Ozzy Osbourne In The Year After He Died",
      "source": "Loudwire (US)",
      "link": "https://loudwire.com/ozzy-osbourne-death-remembered/",
      "summary": "Leon Neal, Getty Images, Angela Weiss, Getty Images, Kevin Winter, Getty Images",
      "date": "2026-07-22T18:46:35",
      "image": ""
    },
    {
      "title": "The Rolling Stones’ Mick Jagger says there’s “nothing good” about getting older",
      "source": "NME News (UK)",
      "link": "https://www.nme.com/news/music/the-rolling-stones-mick-jagger-says-theres-nothing-good-about-getting-older-3958531?utm_source=rss&utm_medium=rss&utm_campaign=the-rolling-stones-mick-jagger-says-theres-nothing-good-about-getting-older",
      "summary": "\"You don’t get wisdom. You forget everything\" The post The Rolling Stones&#8217; Mick Jagger says there&#8217;s &#8220;nothing good&#8221; about getting older appeared first on NME.",
      "date": "2026-07-22T20:36:05",
      "image": ""
    },
    {
      "title": "Tom Morello launches Mary Morello Memorial Project in honour of late mother",
      "source": "NME News (UK)",
      "link": "https://www.nme.com/news/music/tom-morello-launches-mary-morello-memorial-project-in-honour-of-late-mother-3958516?utm_source=rss&utm_medium=rss&utm_campaign=tom-morello-launches-mary-morello-memorial-project-in-honour-of-late-mother",
      "summary": "The Rage Against The Machine guitarist has urged people to “do as Mary did” through “caring, service and action\" The post Tom Morello launches Mary Morello Memorial Project in honour of late mother appeared first on NME.",
      "date": "2026-07-22T17:38:11",
      "image": ""
    }
  ]
}